Metadata-Version: 2.1
Name: mazagui
Version: 0.11
Summary: GUI for cross-platform 2d/3d image segmentation C++ library
Home-page: UNKNOWN
Author: Mathieu Gravey, Roman V. Vasilyev, Timofey Sizonenko, Kirill M. Gerke, Marina V. Karsanina
Author-email: mathieu.gravey@unil.ch
License: GPLv3
Platform: UNKNOWN
Classifier: Development Status :: 3 - Alpha
Classifier: Intended Audience :: Science/Research
Classifier: Intended Audience :: Education
Classifier: License :: OSI Approved :: GNU Lesser General Public License v3 (LGPLv3)
Classifier: Programming Language :: C++
Classifier: Programming Language :: Python :: 3 :: Only
Classifier: Operating System :: OS Independent
License-File: LICENSE.txt
